feagi_agent_mycobot/CMakeLists.txt
feagi_agent_mycobot/__init__.py
feagi_agent_mycobot/__main__.py
feagi_agent_mycobot/package.xml
feagi_agent_mycobot/setup.cfg
feagi_agent_mycobot/setup.py
feagi_agent_mycobot/start_mycobot.sh
feagi_agent_mycobot/src/__init__.py
feagi_agent_mycobot/src/configuration.py
feagi_agent_mycobot/src/mycobot.py
feagi_agent_mycobot/src/version.py
feagi_agent_mycobot-0.0.8.dist-info/LICENSE
feagi_agent_mycobot-0.0.8.dist-info/METADATA
feagi_agent_mycobot-0.0.8.dist-info/WHEEL
feagi_agent_mycobot-0.0.8.dist-info/top_level.txt
feagi_agent_mycobot-0.0.8.dist-info/RECORD
