Metadata-Version: 2.1
Name: feagi_agent_mycobot
Version: 0.0.8
Summary: Feagi agent mycobot to connect feagi with your cobot arm
Home-page: https://github.com/feagi/feagi
Author: Neuraville INC
Author-email: info@neuraville.com
Project-URL: Bug Tracker, https://github.com/feagi/feagi/issues
Classifier: Programming Language :: Python :: 3 :: Only
Classifier: License :: OSI Approved :: Apache Software License
Classifier: Operating System :: OS Independent
Requires-Python: >=3.6
License-File: LICENSE
Requires-Dist: feagi-agent
Requires-Dist: zmq >=0.0.0 ; python_version < "3.8"
